camera4kivy/__init__.py
camera4kivy/preview.py
camera4kivy/preview_camerax.py
camera4kivy/preview_common.py
camera4kivy/preview_kivycamera.py
camera4kivy/based_on_kivy_core/__init__.py
camera4kivy/based_on_kivy_core/camera/__init__.py
camera4kivy/based_on_kivy_core/camera/camera_gi.py
camera4kivy/based_on_kivy_core/camera/camera_opencv.py
camera4kivy/based_on_kivy_core/camera/camera_picamera.py
camera4kivy/based_on_kivy_core/camera/camera_picamera2.py
camera4kivy-0.3.3.dist-info/LICENSE
camera4kivy-0.3.3.dist-info/METADATA
camera4kivy-0.3.3.dist-info/WHEEL
camera4kivy-0.3.3.dist-info/top_level.txt
camera4kivy-0.3.3.dist-info/RECORD
