Metadata-Version: 2.1
Name: camera4kivy
Version: 0.3.3
Summary: Yet Another Camera for Kivy
Home-page: https://github.com/Android-for-Python/Camera4Kivy
Author: Robert Flatt
Classifier: Intended Audience :: Developers
Classifier: Topic :: Software Development :: Build Tools
Classifier: Programming Language :: Python :: 3
Classifier: License :: OSI Approved :: MIT License
Classifier: Operating System :: OS Independent
Requires-Python: >=3.7
License-File: LICENSE
Requires-Dist: gestures4kivy>=0.1.3
